alltheutils/__init__.py
alltheutils/base_exceptions.py
alltheutils/config.py
alltheutils/exceptions.py
alltheutils/instance_config.py
alltheutils/multi_processing.py
alltheutils/types.py
alltheutils/utils.py
alltheutils/cli/__init__.py
alltheutils/cli/_base.py
alltheutils/cli/base.py
alltheutils/cli/dataclasses.py
alltheutils/cli/i18n.py
alltheutils/cli/utils.py
alltheutils-4.0.0.dist-info/METADATA
alltheutils-4.0.0.dist-info/WHEEL
alltheutils-4.0.0.dist-info/top_level.txt
alltheutils-4.0.0.dist-info/RECORD
