Metadata-Version: 2.4
Name: alltheutils
Version: 4.0.0
Summary: None
Maintainer-email: whinyaan <whinyaan@disroot.org>
License-Expression: MIT
Project-URL: homepage, https://python-poetry.org/
Project-URL: repository, https://github.com/whinee/AllTheUtils
Project-URL: documentation, https://github.com/whinee/AllTheUtils/tree/main/docs
Project-URL: Bug Tracker, https://github.com/whinee/AllTheUtils/issues
Keywords: utility
Classifier: Intended Audience :: Developers
Classifier: Natural Language :: English
Classifier: Operating System :: OS Independent
Classifier: Programming Language :: Python :: 3
Classifier: Topic :: Utilities
Requires-Python: >=3.12
Requires-Dist: click>=8.1.3
Requires-Dist: json5>=0.12.0
Requires-Dist: pyyaml>=6.0
Requires-Dist: questionary>=1.10.0
Requires-Dist: semver>=3.0.4
Requires-Dist: tabulate>=0.9.0
Requires-Dist: tomlkit>=0.13.2
